atom_alter_API/__init__.py
atom_alter_API/api.py
atom_alter_API/constants.py
atom_alter_API/exceptions.py
atom_alter_API/utils/__init__.py
atom_alter_API/utils/logging.py
atom_alter_API/utils/mathematical.py
atom_alter_API/utils/xdg.py
atom_alter_api-0.1.4.dist-info/LICENSE
atom_alter_api-0.1.4.dist-info/METADATA
atom_alter_api-0.1.4.dist-info/WHEEL
atom_alter_api-0.1.4.dist-info/top_level.txt
atom_alter_api-0.1.4.dist-info/RECORD
