Metadata-Version: 2.1
Name: atom-alter-api
Version: 0.1.4
Summary: An unofficial python library for communication with the Atomars and Alterdice exchanges API
Home-page: https://github.com/hyperevo/Atomars-alterdice-API
Author: Tommy Mckinnon
Author-email: tommy@HeliosProtocol.io
License: MIT
Platform: UNKNOWN
Requires-Python: >=3.6
Requires-Dist: aiohttp (==3.5.4)
Requires-Dist: eth-utils (==1.8.1)
Provides-Extra: api
Requires-Dist: aiohttp (==3.5.4) ; extra == 'api'
Requires-Dist: eth-utils (==1.8.1) ; extra == 'api'
